fitsblender/__init__.py
fitsblender/acs_header.rules
fitsblender/blender.py
fitsblender/blendheaders.py
fitsblender/hst_header.rules
fitsblender/jwst_header.rules
fitsblender/nicmos_header.rules
fitsblender/nircam_header.rules
fitsblender/nirspec_header.rules
fitsblender/stis_header.rules
fitsblender/wfc3_header.rules
fitsblender/wfpc2_header.rules
fitsblender/pars/blendheaders.cfg
fitsblender/pars/blendheaders.cfgspc
fitsblender/tests/EUVEngc4151imgx.fits
fitsblender/tests/FGSf64y0106m_a1f.fits
fitsblender/tests/FOSy19g0309t_c2f.fits
fitsblender/tests/HRSz0yd020fm_c2f.fits
fitsblender/tests/IUElwp25637mxlo.fits
fitsblender/tests/NICMOSn4hk12010_mos.fits
fitsblender/tests/UITfuv2582gc.fits
fitsblender/tests/WFPC2ASSNu5780205bx.fits
fitsblender/tests/WFPC2u5780205r_c0fx.fits
fitsblender/tests/__init__.py
fitsblender/tests/test_fitsblender.py
fitsblender-0.4.4.dist-info/LICENSE.txt
fitsblender-0.4.4.dist-info/METADATA
fitsblender-0.4.4.dist-info/WHEEL
fitsblender-0.4.4.dist-info/top_level.txt
fitsblender-0.4.4.dist-info/RECORD
